test_sqloxide-0.1.26.dist-info/RECORD
test_sqloxide-0.1.26.dist-info/METADATA
test_sqloxide-0.1.26.dist-info/top_level.txt
test_sqloxide-0.1.26.dist-info/LICENSE
test_sqloxide-0.1.26.dist-info/WHEEL
sqloxide/__init__.py
sqloxide/sqloxide.cpython-37m-powerpc64le-linux-gnu.so
