Metadata-Version: 2.1
Name: test-sqloxide
Version: 0.1.26
Summary: Python bindings for sqlparser-rs
Home-page: https://github.com/wseaton/sqloxide
Author: Will Eaton
Author-email: me@wseaton.com
Requires-Python: >=3.7,<4.0
License-File: LICENSE
